tweets_to_topic_network/__init__.py
tweets_to_topic_network/data.py
tweets_to_topic_network/network.py
tweets_to_topic_network/topic.py
tweets_to_topic_network-0.1.10.dist-info/LICENSE
tweets_to_topic_network-0.1.10.dist-info/METADATA
tweets_to_topic_network-0.1.10.dist-info/WHEEL
tweets_to_topic_network-0.1.10.dist-info/RECORD
