Metadata-Version: 2.1
Name: tweets-to-topic-network
Version: 0.1.10
Summary: start from a set of tweets and create a multilayer network where each layer is a topic
Author: alessiogandelli
Author-email: alessiogandelli99@gmail.com
Requires-Python: >=3.10,<3.13
Classifier: Programming Language :: Python :: 3
Classifier: Programming Language :: Python :: 3.10
Classifier: Programming Language :: Python :: 3.11
Requires-Dist: bertopic (>=0.16.0,<0.17.0)
Requires-Dist: fastembed (>=0.2.6,<0.3.0)
Requires-Dist: flask (>=3.0.3,<4.0.0)
Requires-Dist: igraph (>=0.11.4,<0.12.0)
Requires-Dist: jsonlines (>=4.0.0,<5.0.0)
Requires-Dist: langchain (>=0.1.16,<0.2.0)
Requires-Dist: networkx (>=3.3,<4.0)
Requires-Dist: openai (>=1.17.0,<2.0.0)
Requires-Dist: pandas (>=2.0,<3.0)
Requires-Dist: pipdeptree (>=2.22.0,<3.0.0)
Requires-Dist: qdrant-client (>=1.8.2,<2.0.0)
Requires-Dist: sentence-transformers (>=2.6.1,<3.0.0)
Requires-Dist: tiktoken (>=0.6.0,<0.7.0)
Requires-Dist: typing-extensions (>=4.11.0,<5.0.0)
Requires-Dist: umap-learn (>=0.5.6,<0.6.0)
Requires-Dist: uunet (>=2.1.1,<3.0.0)
